bhopengraph/Edge.py
bhopengraph/Logger.py
bhopengraph/Node.py
bhopengraph/OpenGraph.py
bhopengraph/Properties.py
bhopengraph/__init__.py
bhopengraph/__main__.py
bhopengraph/tests/__init__.py
bhopengraph/tests/datasets/generate.py
bhopengraph/tests/run_tests.py
bhopengraph/tests/test_Edge.py
bhopengraph/tests/test_Node.py
bhopengraph/tests/test_OpenGraph.py
bhopengraph/tests/test_Properties.py
bhopengraph/utils.py
bhopengraph-1.3.0.dist-info/METADATA
bhopengraph-1.3.0.dist-info/WHEEL
bhopengraph-1.3.0.dist-info/entry_points.txt
bhopengraph-1.3.0.dist-info/licenses/LICENSE
bhopengraph-1.3.0.dist-info/RECORD
