Metadata-Version: 2.4
Name: bhopengraph
Version: 1.3.0
Summary: A python library to create BloodHound OpenGraphs easily
License: MIT
License-File: LICENSE
Author: p0dalirius
Requires-Python: >=3.11
Classifier: License :: OSI Approved :: MIT License
Classifier: Programming Language :: Python :: 3
Classifier: Programming Language :: Python :: 3.11
Classifier: Programming Language :: Python :: 3.12
Classifier: Programming Language :: Python :: 3.13
Classifier: Programming Language :: Python :: 3.14
